agents/__init__.py
agents/base.py
agents/antigravity/adapter.py
agents/claude/adapter.py
agents/codex/adapter.py
agents/cursor/adapter.py
agents/gemini/adapter.py
ask/__init__.py
ask/__main__.py
ask/cli.py
ask/commands/__init__.py
ask/commands/add_agent.py
ask/commands/copy.py
ask/commands/create.py
ask/commands/list_skills.py
ask/commands/remove.py
ask/commands/sync.py
ask/commands/update.py
ask/templates/skill/README.md
ask/templates/skill/skill.yaml
ask/utils/__init__.py
ask/utils/agent_registry.py
ask/utils/filesystem.py
ask/utils/skill_registry.py
ask/utils/validators.py
skills/coding/ask-bug-finder/README.md
skills/coding/ask-bug-finder/SKILL.md
skills/coding/ask-bug-finder/skill.yaml
skills/coding/ask-code-reviewer/README.md
skills/coding/ask-code-reviewer/SKILL.md
skills/coding/ask-code-reviewer/skill.yaml
skills/coding/ask-commit-assistance/README.md
skills/coding/ask-commit-assistance/SKILL.md
skills/coding/ask-commit-assistance/skill.yaml
skills/coding/ask-component-scaffolder/README.md
skills/coding/ask-component-scaffolder/SKILL.md
skills/coding/ask-component-scaffolder/skill.yaml
skills/coding/ask-component-scaffolder/scripts/scaffold_component.py
skills/coding/ask-db-migration-assistant/README.md
skills/coding/ask-db-migration-assistant/SKILL.md
skills/coding/ask-db-migration-assistant/skill.yaml
skills/coding/ask-docker-expert/README.md
skills/coding/ask-docker-expert/SKILL.md
skills/coding/ask-docker-expert/skill.yaml
skills/coding/ask-effective-llm-coder/README.md
skills/coding/ask-effective-llm-coder/SKILL.md
skills/coding/ask-effective-llm-coder/skill.yaml
skills/coding/ask-explaining-code/README.md
skills/coding/ask-explaining-code/SKILL.md
skills/coding/ask-explaining-code/skill.yaml
skills/coding/ask-fastapi-architect/README.md
skills/coding/ask-fastapi-architect/SKILL.md
skills/coding/ask-fastapi-architect/skill.yaml
skills/coding/ask-flutter-architect/README.md
skills/coding/ask-flutter-architect/SKILL.md
agent_skill_kit-0.1.1.dist-info/METADATA
agent_skill_kit-0.1.1.dist-info/WHEEL
agent_skill_kit-0.1.1.dist-info/entry_points.txt
agent_skill_kit-0.1.1.dist-info/RECORD
